select_options/__init__.py
select_options/extra.py
select_options/select.py
select_options-0.1.0.dist-info/METADATA
select_options-0.1.0.dist-info/WHEEL
select_options-0.1.0.dist-info/top_level.txt
select_options-0.1.0.dist-info/RECORD
