Metadata-Version: 2.4
Name: select_options
Version: 0.1.0
Summary: A simple library for creating interactive selection menus in terminal applications.
Home-page: 
Author: Gerard Vello
Author-email: gerard.vello@gmail.com
Classifier: Programming Language :: Python :: 3
Classifier: License :: OSI Approved :: MIT License
Classifier: Operating System :: OS Independent
Requires-Python: >=3.7
Requires-Dist: textual
Dynamic: author
Dynamic: author-email
Dynamic: classifier
Dynamic: description
Dynamic: requires-dist
Dynamic: requires-python
Dynamic: summary
